src/bbpd.v
// CHIPATHON 2026
//! @title Bang-Bang Phase Detector
//! @author Muhammad Shofuwan Anwar, Ferhad Zulfas, Hardian Tri Pamungkas, Maulidan Imtinan Ahmada

module bbpd(
    input wire tref, //! reference clock
    input wire tdiv, //! clock from clk_div generated from DCO
    input wire rst_n, //! FF reset

    output reg te //! signal output e[k]
);

    reg q_up, q_down; //! FF output from captured signal
    wire ff_rst; //! combinational reset

    //! This DFF is used to capture the reference signal
    always @(posedge tref or negedge ff_rst) begin: dff_up
        if (~ff_rst)
            q_up <= 1'b0;
        else
            q_up <= 1'b1;
    end

    //! This DFF is used to capture the division signal (signal from clk_div)
    always @(posedge tdiv or negedge ff_rst) begin: dff_down
        if (~ff_rst)
            q_down <= 1'b0;
        else
            q_down <= 1'b1;
    end

    //! This DFF act as "priority encoder", which one is more faster, tref or tdiv
    always @(posedge q_down or negedge rst_n) begin: priority_encoder
        if (~rst_n)
            te <= 1'b0;
        else
            te <= q_up;
    end

    assign ff_rst = ~((q_down & q_up) | ~rst_n); //! combine the reset signal

endmodule

tb/bbpd_tb.v
`define DCO_UP      1

module bbpd_tb;
    reg tref = 0;
    reg tdiv = 0;
    reg rst_n = 0;
    wire te;

    bbpd bbpd0(.tref(tref), .tdiv(tdiv), .rst_n(rst_n), .te(te));

`ifdef DCO_UP
    always #5 tref = ~tref;
`else
    always #5 tdiv = ~tdiv;
`endif

    initial begin
        #1;

`ifdef DCO_UP
        forever #5 tdiv = ~tdiv;
`else
        forever #5 tref = ~tref;
`endif
    end

    initial begin
        $dumpfile("bbpd_tb.vcd");
        $dumpvars(0, bbpd_tb);

        #3 rst_n <= 1;

        #100;
        $finish;
    end
endmodule

tb/bbpd_tb.vcd
$date
	Fri Jul 10 20:10:18 2026
$end
$version
	Icarus Verilog
$end
$timescale
	1ps
$end
$scope module bbpd_tb $end
$var wire 1 ! te $end
$var reg 1 " rst_n $end
$var reg 1 # tdiv $end
$var reg 1 $ tref $end
$scope module bbpd0 $end
$var wire 1 % ff_rst $end
$var wire 1 " rst_n $end
$var wire 1 # tdiv $end
$var wire 1 $ tref $end
$var reg 1 & q_down $end
$var reg 1 ' q_up $end
$var reg 1 ! te $end
$scope begin dff_down $end
$upscope $end
$scope begin dff_up $end
$upscope $end
$scope begin priority_encoder $end
$upscope $end
$upscope $end
$upscope $end
$enddefinitions $end
$comment Show the parameter values. $end
$dumpall
$end
#0
$dumpvars
0'
0&
0%
0$
0#
0"
0!
$end
#10000
1%
1"
#15000
1'
1$
#15500
0$
#17000
0'
1!
1%
0&
1#
#17500
0#
#25000
1'
1$
#25500
0$
#27000
0'
1%
0&
1#
#27500
0#
#35000
1'
1$
#35500
0$
#37000
0'
1%
0&
1#
#37500
0#
#45000
1'
1$
#45500
0$
#47000
0'
1%
0&
1#
#47500
0#
#55000
1'
1$
#55500
0$
#57000
0'
1%
0&
1#
#57500
0#
#85000
0!
1&
1#
#85500
0#
#87000
0&
1%
0'
1$
#87500
0$
#95000
1&
1#
#95500
0#
#97000
0&
1%
0'
1$
#97500
0$
#105000
1&
1#
#105500
0#
#107000
0&
1%
0'
1$
#107500
0$
#115000
1&
1#
#115500
0#
#117000
0&
1%
0'
1$
#117500
0$
#125000
1&
1#
#125500
0#
#127000
0&
1%
0'
1$
#127500
0$
#155000
1'
1$
#155050
0'
1!
1%
0&
1#
#155550
0#
0$
#165000
1'
1$
#165050
0'
1%
0&
1#
#165550
0#
0$
#175000
1'
1$
#175050
0'
1%
0&
1#
#175550
0#
0$
#185000
1'
1$
#185050
0'
1%
0&
1#
#185550
0#
0$
#195000
1'
1$
#195050
0'
1%
0&
1#
#195550
0#
0$
#225000
0!
1&
1#
#225050
0&
1%
0'
1$
#225550
0$
0#
#235000
1&
1#
#235050
0&
1%
0'
1$
#235550
0$
0#
#245000
1&
1#
#245050
0&
1%
0'
1$
#245550
0$
0#
#255000
1&
1#
#255050
0&
1%
0'
1$
#255550
0$
0#
#265000
1&
1#
#265050
0&
1%
0'
1$
#265550
0$
0#
