src/bbpd.v
// CHIPATHON 2026
//! @title Bang-Bang Phase Detector
//! @author Muhammad Shofuwan Anwar, Ferhad Zulfas, Hardian Tri Pamungkas, Maulidan Imtinan Ahmada

module bbpd(
    input wire tref, //! reference clock
    input wire tdiv, //! clock from clk_div generated from DCO
    input wire rst_n, //! FF reset

    output reg te //! signal output e[k]
);

    reg q_up, q_down; //! FF output from captured signal
    wire ff_rst; //! combinational reset

    //! This DFF is used to capture the reference signal
    always @(posedge tref or negedge ff_rst) begin: dff_up
        if (~ff_rst)
            q_up <= 1'b0;
        else
            q_up <= 1'b1;
    end

    //! This DFF is used to capture the division signal (signal from clk_div)
    always @(posedge tdiv or negedge ff_rst) begin: dff_down
        if (~ff_rst)
            q_down <= 1'b0;
        else
            q_down <= 1'b1;
    end

    //! This DFF act as "priority encoder", which one is more faster, tref or tdiv
    always @(posedge q_down or negedge rst_n) begin: priority_encoder
        if (~rst_n)
            te <= 1'b0;
        else
            te <= q_up;
    end

    assign ff_rst = ~((q_down & q_up) | ~rst_n); //! combine the reset signal

endmodule

tb/bbpd_tb.v
`define DCO_UP      1

module bbpd_tb;
    reg tref = 0;
    reg tdiv = 0;
    reg rst_n = 0;
    wire te;

    bbpd bbpd0(.tref(tref), .tdiv(tdiv), .rst_n(rst_n), .te(te));

`ifdef DCO_UP
    always #5 tref = ~tref;
`else
    always #5 tdiv = ~tdiv;
`endif

    initial begin
        #1;

`ifdef DCO_UP
        forever #5 tdiv = ~tdiv;
`else
        forever #5 tref = ~tref;
`endif
    end

    initial begin
        $dumpfile("bbpd_tb.vcd");
        $dumpvars(0, bbpd_tb);

        #3 rst_n <= 1;

        #100;
        $finish;
    end
endmodule

tb/bbpd_tb.vcd
$date
	Sat Jun 20 05:09:26 2026
$end
$version
	Icarus Verilog
$end
$timescale
	1s
$end
$scope module bbpd_tb $end
$var wire 1 ! te $end
$var reg 1 " rst_n $end
$var reg 1 # tdiv $end
$var reg 1 $ tref $end
$scope module bbpd0 $end
$var wire 1 % ff_rst $end
$var wire 1 " rst_n $end
$var wire 1 # tdiv $end
$var wire 1 $ tref $end
$var reg 1 & q_down $end
$var reg 1 ' q_up $end
$var reg 1 ! te $end
$scope begin dff_down $end
$upscope $end
$scope begin dff_up $end
$upscope $end
$scope begin priority_encoder $end
$upscope $end
$upscope $end
$upscope $end
$enddefinitions $end
$comment Show the parameter values. $end
$dumpall
$end
#0
$dumpvars
0'
0&
0%
0$
0#
0"
0!
$end
#3
1%
1"
#5
1'
1$
#6
0'
1!
1%
0&
1#
#10
0$
#11
0#
#15
1'
1$
#16
0'
1%
0&
1#
#20
0$
#21
0#
#25
1'
1$
#26
0'
1%
0&
1#
#30
0$
#31
0#
#35
1'
1$
#36
0'
1%
0&
1#
#40
0$
#41
0#
#45
1'
1$
#46
0'
1%
0&
1#
#50
0$
#51
0#
#55
1'
1$
#56
0'
1%
0&
1#
#60
0$
#61
0#
#65
1'
1$
#66
0'
1%
0&
1#
#70
0$
#71
0#
#75
1'
1$
#76
0'
1%
0&
1#
#80
0$
#81
0#
#85
1'
1$
#86
0'
1%
0&
1#
#90
0$
#91
0#
#95
1'
1$
#96
0'
1%
0&
1#
#100
0$
#101
0#
