src/bbpd.v
// CHIPATHON 2026
//! @title Bang-Bang Phase Detector
//! @author Muhammad Shofuwan Anwar, Ferhad Zulfas, Hardian Tri Pamungkas, Maulidan Imtinan Ahmada

module bbpd(
    input wire tref, //! reference clock
    input wire tdiv, //! clock from clk_div generated from DCO
    input wire rst_n, //! FF reset

    output reg te //! signal output e[k]
);

    reg q_ref, q_div; //! FF output from captured signal
    wire ff_rst; //! combinational reset

    //! This DFF is used to capture the reference signal
    always @(posedge tref or negedge ff_rst) begin: dff_up
        if (~ff_rst)
            q_ref <= 1'b0;
        else
            q_ref <= 1'b1;
    end

    //! This DFF is used to capture the division signal (signal from clk_div)
    always @(posedge tdiv or negedge ff_rst) begin: dff_down
        if (~ff_rst)
            q_div <= 1'b0;
        else
            q_div <= 1'b1;
    end

    //! This DFF act as "priority encoder", which one is more faster, tref or tdiv
    always @(posedge q_div or negedge rst_n) begin: priority_encoder
        if (~rst_n)
            te <= 1'b0;
        else
            te <= q_ref;
    end

    assign ff_rst = ~(~(tref & tdiv) | rst_n); //! NAND and NOR to combine the reset signal

endmodule

tb/bbpd_tb.v
module bbpd_tb;
    reg tref = 0;
    reg tdiv = 0;
    reg rst_n = 1;
    wire te;

    bbpd bbpd0(.tref(tref), .tdiv(tdiv), .rst_n(rst_n), .te(te));

    integer x;
    initial begin
        $dumpfile("bbpd_tb.vcd");
        $dumpvars(0, bbpd_tb);
        
        #10 rst_n <= 0;
        #10 rst_n <= 1;

        for (x=0; x<5; x=x+1) begin
            #10 tref <= ~tref;
            #11 tdiv <= ~tref;
        end

        for (x=0; x<5; x=x+1) begin
            #11 tref <= ~tref;
            #10 tdiv <= ~tref;
        end
    end
endmodule

tb/bbpd_tb.vcd
$date
	Fri Jun 19 09:34:21 2026
$end
$version
	Icarus Verilog
$end
$timescale
	1s
$end
$scope module bbpd_tb $end
$var wire 1 ! te $end
$var reg 1 " rst_n $end
$var reg 1 # tdiv $end
$var reg 1 $ tref $end
$var integer 32 % x [31:0] $end
$scope module bbpd0 $end
$var wire 1 & ff_rst $end
$var wire 1 " rst_n $end
$var wire 1 # tdiv $end
$var wire 1 $ tref $end
$var reg 1 ' q_div $end
$var reg 1 ( q_ref $end
$var reg 1 ! te $end
$scope begin dff_down $end
$upscope $end
$scope begin dff_up $end
$upscope $end
$scope begin priority_encoder $end
$upscope $end
$upscope $end
$upscope $end
$enddefinitions $end
$comment Show the parameter values. $end
$dumpall
$end
#0
$dumpvars
0(
0'
0&
bx %
0$
0#
1"
x!
$end
#10
0!
0"
#20
1"
b0 %
#30
1$
#41
b1 %
#51
0$
#62
1#
b10 %
#72
1$
#83
0#
b11 %
#93
0$
#104
1#
b100 %
#114
1$
#125
0#
b0 %
#136
0$
#146
1#
b1 %
#157
1$
#167
0#
b10 %
#178
0$
#188
1#
b11 %
#199
1$
#209
0#
b100 %
#220
0$
#230
1#
b101 %
