src/dlf_pi.v
// CHIPATHON 2026
//! @title LFSR Generator for Dithering
//! @author Muhammad Shofuwan Anwar, Ferhad Zulfas, Hardian Tri Pamungkas, Maulidan Imtinan Ahmada

module dlf_pi #(
    parameter integer DCO_W = 10,   //! DCO control word width
    parameter integer FRAC  = 8     //! fractional bits (sub-LSB integral)
)(
    input  wire                clk_ref,      //! reference clock
    input  wire                rst_n,        //! async reset, active low
    input  wire                te_raw,       //! e[k] from bbpd
    input  wire [3:0]          kp,           //! beta  = 2^kp
    input  wire [3:0]          ki,           //! alpha = 2^-ki
    input  wire                dither_en,    //! enable dither
    input  wire signed [5:0]   dither,       //! signed dither, LSB units
    output reg  [DCO_W-1:0]    dco_code,     //! word to DCO
    output wire                te_sync       //! te sync
);

    localparam integer GUARD = 4;
    localparam integer AW    = DCO_W + FRAC + GUARD;

    localparam signed [AW-1:0]   ACC_MAX  = ((1 <<< (DCO_W-1)) - 1) <<< FRAC;
    localparam signed [AW-1:0]   ACC_MIN  = -ACC_MAX;
    localparam signed [AW+1:0]   CODE_MAX = (1 <<< DCO_W) - 1;
    localparam signed [AW+1:0]   CODE_MID = (1 <<< (DCO_W-1));

    reg                  te_ff;        //! te flip flop
    reg  signed [AW-1:0] acc;          //! integral accumulator

    wire [4:0]           kp_sh;        //! clamped proportional
    wire [4:0]           ki_sh;        //! clamped integral
    wire signed [AW-1:0] prop_mag;     //! proportional step magnitude (beta)
    wire signed [AW-1:0] prop_step;    //! signed proportional step (+/- beta)
    wire signed [AW-1:0] integ_mag;    //! integral step magnitude (alpha)
    wire signed [AW-1:0] integ_step;   //! signed integral step (+/- alpha)
    wire signed [AW:0]   acc_next;     //! accumulator next value (1 bit wider)
    wire                 acc_over;     //! acc_next above upper saturation limit
    wire                 acc_under;    //! acc_next below lower saturation limit
    wire signed [AW+1:0] dith_val;     //! dither shifted to DCO-LSB alignment
    wire signed [AW+1:0] pi_sum;       //! integral + proportional
    wire signed [AW+1:0] full_sum;     //! pi_sum + dither
    wire signed [AW+1:0] code_val;     //! DCO before clamp

    always @(posedge clk_ref or negedge rst_n) begin : sync_te
        if (!rst_n) 
            te_ff <= 1'b0;
        else        
            te_ff <= te_raw;
    end

    assign te_sync   = te_ff;

    assign kp_sh     = (kp > (DCO_W+GUARD-2)) ? (DCO_W+GUARD-2) : kp;
    assign ki_sh     = (ki > FRAC)            ? FRAC            : ki;

    assign prop_mag  = $signed(1) <<< (FRAC + kp_sh);
    assign prop_step = te_ff ? prop_mag : -prop_mag;

    assign integ_mag  = $signed(1) <<< (FRAC - ki_sh);
    assign integ_step = te_ff ? integ_mag : -integ_mag;

    assign acc_next  = acc + integ_step;

    always @(posedge clk_ref or negedge rst_n) begin : integrator
        if (!rst_n)
            acc <= 0;
        else if (acc_next > ACC_MAX)  
            acc <= ACC_MAX;
        else if (acc_next < ACC_MIN) 
            acc <= ACC_MIN;
        else                
            acc <= acc_next;
    end

    assign dith_val  = dither_en ? (dither <<< FRAC) : 0;

    assign pi_sum    = acc + prop_step;
    assign full_sum  = pi_sum + dith_val;
    assign code_val  = (full_sum >>> FRAC) + CODE_MID;


    always @(posedge clk_ref or negedge rst_n) begin : output_reg
        if (!rst_n)
            dco_code <= CODE_MID[DCO_W-1:0];
        else if (code_val < 0)  
            dco_code <= 0;
        else if (code_val > CODE_MAX) 
            dco_code <= CODE_MAX[DCO_W-1:0];
        else                
            dco_code <= code_val[DCO_W-1:0];
    end

endmodule

tb/dlf_pi_tb.v
`timescale 1ns/1ps

module tb_dlf_pi;

    // DUT Parameters
    parameter integer DCO_W = 10;
    parameter integer FRAC  = 8;

    // Testbench signals
    reg clk = 0;
    reg rst_n = 0;
    reg te_raw = 0;
    reg [3:0] kp = 0;
    reg [3:0] ki = 0;
    reg dither_en = 0;
    reg signed [5:0] dither = 0;
    
    wire [DCO_W-1:0] dco_code;
    wire te_sync;

    // Clock generator (50MHz reference clock)
    always #10 clk = ~clk;

    // DLF-PI Device Under Test (DUT) Instantiation
    dlf_pi #(
        .DCO_W(DCO_W),
        .FRAC(FRAC)
    ) dut (
        .clk_ref(clk),
        .rst_n(rst_n),
        .te_raw(te_raw),
        .kp(kp),
        .ki(ki),
        .dither_en(dither_en),
        .dither(dither),
        .dco_code(dco_code),
        .te_sync(te_sync)
    );

    initial begin
        // Setup VCD dump for waveform analysis
        $dumpfile("dlf_pi.vcd");
        $dumpvars(0, tb_dlf_pi);
        
        $display("=============================================================");
        $display("STARTING DLF-PI VERIFICATION (MBG32)");
        $display("=============================================================");

        // INITIAL CONDITION: Assert reset
        rst_n = 0;
        te_raw = 0;
        kp = 4'd2; // Moderate Proportional gain
        ki = 4'd4; // Moderate Integral gain
        dither_en = 0;
        dither = 6'd0;
        #100;

        // TEST 1: Reset behavior and initial proportional step check
        // Expected: 512 - 4 = 508 due to instantaneous negative proportional step (te_raw=0)
        $display("[TEST 1] Reset Release & Initial Proportional Step Check");
        rst_n = 1;
        #20;
        if (dco_code == 10'd508)
            $display("-> PASSED: Output correctly stepped to 508 due to BBPD behavior.");
        else
            $display("-> FAILED: Output is %0d (Expected: 508).", dco_code);

        // TEST 2: Positive Phase Error (te_raw = 1) Accumulation
        $display("[TEST 2] Positive Accumulation (te_raw = 1)");
        te_raw = 1;
        #1000;
        $display("-> Current DCO Code after short accumulation: %0d", dco_code);

        // TEST 3: Upper Saturation/Clamping Check
        // Extended delay to allow the slow integrator to reach ACC_MAX
        $display("[TEST 3] Forcing Upper Saturation (Code MAX)");
        kp = 4'd6; 
        ki = 4'd2; // Faster integral step to guarantee saturation
        te_raw = 1;
        #60000; // Increased delay to ensure full accumulator saturation
        if (dco_code == 10'd1023)
            $display("-> PASSED: DCO safely clamped at MAX (1023) without overflow.");
        else
            $display("-> FAILED: DCO code at saturation is %0d (Expected: 1023).", dco_code);

        // TEST 4: Negative Phase Error (te_raw = 0) Accumulation
        $display("[TEST 4] Negative Accumulation (te_raw = 0)");
        te_raw = 0;
        #5000;
        $display("-> Current DCO Code dropping from saturation: %0d", dco_code);

        // TEST 5: Lower Saturation/Clamping Check
        // Extended delay to allow full discharge down to ACC_MIN
        $display("[TEST 5] Forcing Lower Saturation (Code MIN)");
        te_raw = 0;
        #80000; // Increased delay to ensure full accumulator depletion
        if (dco_code == 10'd0)
            $display("-> PASSED: DCO safely clamped at MIN (0) without underflow.");
        else
            $display("-> FAILED: DCO code at saturation is %0d (Expected: 0).", dco_code);

        // TEST 6: Dither Injection test
        $display("[TEST 6] Dither Injection test");
        
        // Reset to center first
        rst_n = 0;
        #50;
        rst_n = 1;
        #50;
        
        dither_en = 1;
        dither = 6'd15; // Inject positive dither
        #50;
        $display("-> Code with +15 Dither injection: %0d", dco_code);
        
        dither = -6'sd10; // Inject negative dither
        #50;
        $display("-> Code with -10 Dither injection: %0d", dco_code);

        $display("=============================================================");
        $display("VERIFICATION COMPLETE");
        $display("=============================================================");
        $finish;
    end

endmodule

tb/dlf_pi.vcd
$date
	Fri Jul 10 20:35:54 2026
$end
$version
	Icarus Verilog
$end
$timescale
	1ps
$end
$scope module tb_dlf_pi $end
$var wire 1 ! te_sync $end
$var wire 10 " dco_code [9:0] $end
$var parameter 32 # DCO_W $end
$var parameter 32 $ FRAC $end
$var reg 1 % clk $end
$var reg 6 & dither [5:0] $end
$var reg 1 ' dither_en $end
$var reg 4 ( ki [3:0] $end
$var reg 4 ) kp [3:0] $end
$var reg 1 * rst_n $end
$var reg 1 + te_raw $end
$scope module dut $end
$var wire 1 % clk_ref $end
$var wire 6 , dither [5:0] $end
$var wire 1 ' dither_en $end
$var wire 4 - ki [3:0] $end
$var wire 4 . kp [3:0] $end
$var wire 1 * rst_n $end
$var wire 1 + te_raw $end
$var wire 1 ! te_sync $end
$var wire 22 / prop_step [21:0] $end
$var wire 22 0 prop_mag [21:0] $end
$var wire 24 1 pi_sum [23:0] $end
$var wire 5 2 kp_sh [4:0] $end
$var wire 5 3 ki_sh [4:0] $end
$var wire 22 4 integ_step [21:0] $end
$var wire 22 5 integ_mag [21:0] $end
$var wire 24 6 full_sum [23:0] $end
$var wire 24 7 dith_val [23:0] $end
$var wire 24 8 code_val [23:0] $end
$var wire 23 9 acc_next [22:0] $end
$var parameter 22 : ACC_MAX $end
$var parameter 22 ; ACC_MIN $end
$var parameter 32 < AW $end
$var parameter 24 = CODE_MAX $end
$var parameter 24 > CODE_MID $end
$var parameter 32 ? DCO_W $end
$var parameter 32 @ FRAC $end
$var parameter 32 A GUARD $end
$var reg 22 B acc [21:0] $end
$var reg 10 C dco_code [9:0] $end
$var reg 1 D te_ff $end
$scope begin integrator $end
$upscope $end
$scope begin output_reg $end
$upscope $end
$scope begin sync_te $end
$upscope $end
$upscope $end
$upscope $end
$enddefinitions $end
$comment Show the parameter values. $end
$dumpall
b100 A
b1000 @
b1010 ?
b1000000000 >
b1111111111 =
b10110 <
b1111100000000100000000 ;
b11111111100000000 :
b1000 $
b1010 #
$end
#0
$dumpvars
0D
b1000000000 C
b0 B
b11111111111111111110000 9
b111111100 8
b0 7
b111111111111110000000000 6
b10000 5
b1111111111111111110000 4
b100 3
b10 2
b111111111111110000000000 1
b10000000000 0
b1111111111110000000000 /
b10 .
b100 -
b0 ,
0+
0*
b10 )
b100 (
0'
b0 &
0%
b1000000000 "
0!
$end
#10000
1%
#20000
0%
#30000
1%
#40000
0%
#50000
1%
#60000
0%
#70000
1%
#80000
0%
#90000
1%
#100000
0%
1*
#110000
b111111011 8
b111111100 "
b111111100 C
b11111111111111111100000 9
b111111111111101111110000 6
b111111111111101111110000 1
b1111111111111111110000 B
1%
#120000
0%
1+
#130000
b1000000011 8
b10000000000 /
b10000 4
b111111011 "
b111111011 C
b11111111111111111110000 9
b1111100000 6
b1111100000 1
b1111111111111111100000 B
1!
1D
1%
#140000
0%
#150000
b1000000011 "
b1000000011 C
b0 9
b1111110000 6
b1111110000 1
b1111111111111111110000 B
1%
#160000
0%
#170000
b1000000100 8
b10000 9
b10000000000 6
b10000000000 1
b0 B
1%
#180000
0%
#190000
b1000000100 "
b1000000100 C
b100000 9
b10000010000 6
b10000010000 1
b10000 B
1%
#200000
0%
#210000
b110000 9
b10000100000 6
b10000100000 1
b100000 B
1%
#220000
0%
#230000
b1000000 9
b10000110000 6
b10000110000 1
b110000 B
1%
#240000
0%
#250000
b1010000 9
b10001000000 6
b10001000000 1
b1000000 B
1%
#260000
0%
#270000
b1100000 9
b10001010000 6
b10001010000 1
b1010000 B
1%
#280000
0%
#290000
b1110000 9
b10001100000 6
b10001100000 1
b1100000 B
1%
#300000
0%
#310000
b10000000 9
b10001110000 6
b10001110000 1
b1110000 B
1%
#320000
0%
#330000
b10010000 9
b10010000000 6
b10010000000 1
b10000000 B
1%
#340000
0%
#350000
b10100000 9
b10010010000 6
b10010010000 1
b10010000 B
1%
#360000
0%
#370000
b10110000 9
b10010100000 6
b10010100000 1
b10100000 B
1%
#380000
0%
#390000
b11000000 9
b10010110000 6
b10010110000 1
b10110000 B
1%
#400000
0%
#410000
b11010000 9
b10011000000 6
b10011000000 1
b11000000 B
1%
#420000
0%
#430000
b11100000 9
b10011010000 6
b10011010000 1
b11010000 B
1%
#440000
0%
#450000
b11110000 9
b10011100000 6
b10011100000 1
b11100000 B
1%
#460000
0%
#470000
b100000000 9
b10011110000 6
b10011110000 1
b11110000 B
1%
#480000
0%
#490000
b1000000101 8
b100010000 9
b10100000000 6
b10100000000 1
b100000000 B
1%
#500000
0%
#510000
b1000000101 "
b1000000101 C
b100100000 9
b10100010000 6
b10100010000 1
b100010000 B
1%
#520000
0%
#530000
b100110000 9
b10100100000 6
b10100100000 1
b100100000 B
1%
#540000
0%
#550000
b101000000 9
b10100110000 6
b10100110000 1
b100110000 B
1%
#560000
0%
#570000
b101010000 9
b10101000000 6
b10101000000 1
b101000000 B
1%
#580000
0%
#590000
b101100000 9
b10101010000 6
b10101010000 1
b101010000 B
1%
#600000
0%
#610000
b101110000 9
b10101100000 6
b10101100000 1
b101100000 B
1%
#620000
0%
#630000
b110000000 9
b10101110000 6
b10101110000 1
b101110000 B
1%
#640000
0%
#650000
b110010000 9
b10110000000 6
b10110000000 1
b110000000 B
1%
#660000
0%
#670000
b110100000 9
b10110010000 6
b10110010000 1
b110010000 B
1%
#680000
0%
#690000
b110110000 9
b10110100000 6
b10110100000 1
b110100000 B
1%
#700000
0%
#710000
b111000000 9
b10110110000 6
b10110110000 1
b110110000 B
1%
#720000
0%
#730000
b111010000 9
b10111000000 6
b10111000000 1
b111000000 B
1%
#740000
0%
#750000
b111100000 9
b10111010000 6
b10111010000 1
b111010000 B
1%
#760000
0%
#770000
b111110000 9
b10111100000 6
b10111100000 1
b111100000 B
1%
#780000
0%
#790000
b1000000000 9
b10111110000 6
b10111110000 1
b111110000 B
1%
#800000
0%
#810000
b1000000110 8
b1000010000 9
b11000000000 6
b11000000000 1
b1000000000 B
1%
#820000
0%
#830000
b1000000110 "
b1000000110 C
b1000100000 9
b11000010000 6
b11000010000 1
b1000010000 B
1%
#840000
0%
#850000
b1000110000 9
b11000100000 6
b11000100000 1
b1000100000 B
1%
#860000
0%
#870000
b1001000000 9
b11000110000 6
b11000110000 1
b1000110000 B
1%
#880000
0%
#890000
b1001010000 9
b11001000000 6
b11001000000 1
b1001000000 B
1%
#900000
0%
#910000
b1001100000 9
b11001010000 6
b11001010000 1
b1001010000 B
1%
#920000
0%
#930000
b1001110000 9
b11001100000 6
b11001100000 1
b1001100000 B
1%
#940000
0%
#950000
b1010000000 9
b11001110000 6
b11001110000 1
b1001110000 B
1%
#960000
0%
#970000
b1010010000 9
b11010000000 6
b11010000000 1
b1010000000 B
1%
#980000
0%
#990000
b1010100000 9
b11010010000 6
b11010010000 1
b1010010000 B
1%
#1000000
0%
#1010000
b1010110000 9
b11010100000 6
b11010100000 1
b1010100000 B
1%
#1020000
0%
#1030000
b1011000000 9
b11010110000 6
b11010110000 1
b1010110000 B
1%
#1040000
0%
#1050000
b1011010000 9
b11011000000 6
b11011000000 1
b1011000000 B
1%
#1060000
0%
#1070000
b1011100000 9
b11011010000 6
b11011010000 1
b1011010000 B
1%
#1080000
0%
#1090000
b1011110000 9
b11011100000 6
b11011100000 1
b1011100000 B
1%
#1100000
0%
#1110000
b1100000000 9
b11011110000 6
b11011110000 1
b1011110000 B
1%
#1120000
b1001000010 8
b1100110000 9
b1000000 4
b100001011110000 6
b100001011110000 1
b100000000000000 /
b1000000 5
b100000000000000 0
b10 3
b110 2
0%
b10 (
b10 -
b110 )
b110 .
#1130000
b1001000011 8
b1001000010 "
b1001000010 C
b1101110000 9
b100001100110000 6
b100001100110000 1
b1100110000 B
1%
#1140000
0%
#1150000
b1001000011 "
b1001000011 C
b1110110000 9
b100001101110000 6
b100001101110000 1
b1101110000 B
1%
#1160000
0%
#1170000
b1111110000 9
b100001110110000 6
b100001110110000 1
b1110110000 B
1%
#1180000
0%
#1190000
b10000110000 9
b100001111110000 6
b100001111110000 1
b1111110000 B
1%
#1200000
0%
#1210000
b1001000100 8
b10001110000 9
b100010000110000 6
b100010000110000 1
b10000110000 B
1%
#1220000
0%
#1230000
b1001000100 "
b1001000100 C
b10010110000 9
b100010001110000 6
b100010001110000 1
b10001110000 B
1%
#1240000
0%
#1250000
b10011110000 9
b100010010110000 6
b100010010110000 1
b10010110000 B
1%
#1260000
0%
#1270000
b10100110000 9
b100010011110000 6
b100010011110000 1
b10011110000 B
1%
#1280000
0%
#1290000
b1001000101 8
b10101110000 9
b100010100110000 6
b100010100110000 1
b10100110000 B
1%
#1300000
0%
#1310000
b1001000101 "
b1001000101 C
b10110110000 9
b100010101110000 6
b100010101110000 1
b10101110000 B
1%
#1320000
0%
#1330000
b10111110000 9
b100010110110000 6
b100010110110000 1
b10110110000 B
1%
#1340000
0%
#1350000
b11000110000 9
b100010111110000 6
b100010111110000 1
b10111110000 B
1%
#1360000
0%
#1370000
b1001000110 8
b11001110000 9
b100011000110000 6
b100011000110000 1
b11000110000 B
1%
#1380000
0%
#1390000
b1001000110 "
b1001000110 C
b11010110000 9
b100011001110000 6
b100011001110000 1
b11001110000 B
1%
#1400000
0%
#1410000
b11011110000 9
b100011010110000 6
b100011010110000 1
b11010110000 B
1%
#1420000
0%
#1430000
b11100110000 9
b100011011110000 6
b100011011110000 1
b11011110000 B
1%
#1440000
0%
#1450000
b1001000111 8
b11101110000 9
b100011100110000 6
b100011100110000 1
b11100110000 B
1%
#1460000
0%
#1470000
b1001000111 "
b1001000111 C
b11110110000 9
b100011101110000 6
b100011101110000 1
b11101110000 B
1%
#1480000
0%
#1490000
b11111110000 9
b100011110110000 6
b100011110110000 1
b11110110000 B
1%
#1500000
0%
#1510000
b100000110000 9
b100011111110000 6
b100011111110000 1
b11111110000 B
1%
#1520000
0%
#1530000
b1001001000 8
b100001110000 9
b100100000110000 6
b100100000110000 1
b100000110000 B
1%
#1540000
0%
#1550000
b1001001000 "
b1001001000 C
b100010110000 9
b100100001110000 6
b100100001110000 1
b100001110000 B
1%
#1560000
0%
#1570000
b100011110000 9
b100100010110000 6
b100100010110000 1
b100010110000 B
1%
#1580000
0%
#1590000
b100100110000 9
b100100011110000 6
b100100011110000 1
b100011110000 B
1%
#1600000
0%
#1610000
b1001001001 8
b100101110000 9
b100100100110000 6
b100100100110000 1
b100100110000 B
1%
#1620000
0%
#1630000
b1001001001 "
b1001001001 C
b100110110000 9
b100100101110000 6
b100100101110000 1
b100101110000 B
1%
#1640000
0%
#1650000
b100111110000 9
b100100110110000 6
b100100110110000 1
b100110110000 B
1%
#1660000
0%
#1670000
b101000110000 9
b100100111110000 6
b100100111110000 1
b100111110000 B
1%
#1680000
0%
#1690000
b1001001010 8
b101001110000 9
b100101000110000 6
b100101000110000 1
b101000110000 B
1%
#1700000
0%
#1710000
b1001001010 "
b1001001010 C
b101010110000 9
b100101001110000 6
b100101001110000 1
b101001110000 B
1%
#1720000
0%
#1730000
b101011110000 9
b100101010110000 6
b100101010110000 1
b101010110000 B
1%
#1740000
0%
#1750000
b101100110000 9
b100101011110000 6
b100101011110000 1
b101011110000 B
1%
#1760000
0%
#1770000
b1001001011 8
b101101110000 9
b100101100110000 6
b100101100110000 1
b101100110000 B
1%
#1780000
0%
#1790000
b1001001011 "
b1001001011 C
b101110110000 9
b100101101110000 6
b100101101110000 1
b101101110000 B
1%
#1800000
0%
#1810000
b101111110000 9
b100101110110000 6
b100101110110000 1
b101110110000 B
1%
#1820000
0%
#1830000
b110000110000 9
b100101111110000 6
b100101111110000 1
b101111110000 B
1%
#1840000
0%
#1850000
b1001001100 8
b110001110000 9
b100110000110000 6
b100110000110000 1
b110000110000 B
1%
#1860000
0%
#1870000
b1001001100 "
b1001001100 C
b110010110000 9
b100110001110000 6
b100110001110000 1
b110001110000 B
1%
#1880000
0%
#1890000
b110011110000 9
b100110010110000 6
b100110010110000 1
b110010110000 B
1%
#1900000
0%
#1910000
b110100110000 9
b100110011110000 6
b100110011110000 1
b110011110000 B
1%
#1920000
0%
#1930000
b1001001101 8
b110101110000 9
b100110100110000 6
b100110100110000 1
b110100110000 B
1%
#1940000
0%
#1950000
b1001001101 "
b1001001101 C
b110110110000 9
b100110101110000 6
b100110101110000 1
b110101110000 B
1%
#1960000
0%
#1970000
b110111110000 9
b100110110110000 6
b100110110110000 1
b110110110000 B
1%
#1980000
0%
#1990000
b111000110000 9
b100110111110000 6
b100110111110000 1
b110111110000 B
1%
#2000000
0%
#2010000
b1001001110 8
b111001110000 9
b100111000110000 6
b100111000110000 1
b111000110000 B
1%
#2020000
0%
#2030000
b1001001110 "
b1001001110 C
b111010110000 9
b100111001110000 6
b100111001110000 1
b111001110000 B
1%
#2040000
0%
#2050000
b111011110000 9
b100111010110000 6
b100111010110000 1
b111010110000 B
1%
#2060000
0%
#2070000
b111100110000 9
b100111011110000 6
b100111011110000 1
b111011110000 B
1%
#2080000
0%
#2090000
b1001001111 8
b111101110000 9
b100111100110000 6
b100111100110000 1
b111100110000 B
1%
#2100000
0%
#2110000
b1001001111 "
b1001001111 C
b111110110000 9
b100111101110000 6
b100111101110000 1
b111101110000 B
1%
#2120000
0%
#2130000
b111111110000 9
b100111110110000 6
b100111110110000 1
b111110110000 B
1%
#2140000
0%
#2150000
b1000000110000 9
b100111111110000 6
b100111111110000 1
b111111110000 B
1%
#2160000
0%
#2170000
b1001010000 8
b1000001110000 9
b101000000110000 6
b101000000110000 1
b1000000110000 B
1%
#2180000
0%
#2190000
b1001010000 "
b1001010000 C
b1000010110000 9
b101000001110000 6
b101000001110000 1
b1000001110000 B
1%
#2200000
0%
#2210000
b1000011110000 9
b101000010110000 6
b101000010110000 1
b1000010110000 B
1%
#2220000
0%
#2230000
b1000100110000 9
b101000011110000 6
b101000011110000 1
b1000011110000 B
1%
#2240000
0%
#2250000
b1001010001 8
b1000101110000 9
b101000100110000 6
b101000100110000 1
b1000100110000 B
1%
#2260000
0%
#2270000
b1001010001 "
b1001010001 C
b1000110110000 9
b101000101110000 6
b101000101110000 1
b1000101110000 B
1%
#2280000
0%
#2290000
b1000111110000 9
b101000110110000 6
b101000110110000 1
b1000110110000 B
1%
#2300000
0%
#2310000
b1001000110000 9
b101000111110000 6
b101000111110000 1
b1000111110000 B
1%
#2320000
0%
#2330000
b1001010010 8
b1001001110000 9
b101001000110000 6
b101001000110000 1
b1001000110000 B
1%
#2340000
0%
#2350000
b1001010010 "
b1001010010 C
b1001010110000 9
b101001001110000 6
b101001001110000 1
b1001001110000 B
1%
#2360000
0%
#2370000
b1001011110000 9
b101001010110000 6
b101001010110000 1
b1001010110000 B
1%
#2380000
0%
#2390000
b1001100110000 9
b101001011110000 6
b101001011110000 1
b1001011110000 B
1%
#2400000
0%
#2410000
b1001010011 8
b1001101110000 9
b101001100110000 6
b101001100110000 1
b1001100110000 B
1%
#2420000
0%
#2430000
b1001010011 "
b1001010011 C
b1001110110000 9
b101001101110000 6
b101001101110000 1
b1001101110000 B
1%
#2440000
0%
#2450000
b1001111110000 9
b101001110110000 6
b101001110110000 1
b1001110110000 B
1%
#2460000
0%
#2470000
b1010000110000 9
b101001111110000 6
b101001111110000 1
b1001111110000 B
1%
#2480000
0%
#2490000
b1001010100 8
b1010001110000 9
b101010000110000 6
b101010000110000 1
b1010000110000 B
1%
#2500000
0%
#2510000
b1001010100 "
b1001010100 C
b1010010110000 9
b101010001110000 6
b101010001110000 1
b1010001110000 B
1%
#2520000
0%
#2530000
b1010011110000 9
b101010010110000 6
b101010010110000 1
b1010010110000 B
1%
#2540000
0%
#2550000
b1010100110000 9
b101010011110000 6
b101010011110000 1
b1010011110000 B
1%
#2560000
0%
#2570000
b1001010101 8
b1010101110000 9
b101010100110000 6
b101010100110000 1
b1010100110000 B
1%
#2580000
0%
#2590000
b1001010101 "
b1001010101 C
b1010110110000 9
b101010101110000 6
b101010101110000 1
b1010101110000 B
1%
#2600000
0%
#2610000
b1010111110000 9
b101010110110000 6
b101010110110000 1
b1010110110000 B
1%
#2620000
0%
#2630000
b1011000110000 9
b101010111110000 6
b101010111110000 1
b1010111110000 B
1%
#2640000
0%
#2650000
b1001010110 8
b1011001110000 9
b101011000110000 6
b101011000110000 1
b1011000110000 B
1%
#2660000
0%
#2670000
b1001010110 "
b1001010110 C
b1011010110000 9
b101011001110000 6
b101011001110000 1
b1011001110000 B
1%
#2680000
0%
#2690000
b1011011110000 9
b101011010110000 6
b101011010110000 1
b1011010110000 B
1%
#2700000
0%
#2710000
b1011100110000 9
b101011011110000 6
b101011011110000 1
b1011011110000 B
1%
#2720000
0%
#2730000
b1001010111 8
b1011101110000 9
b101011100110000 6
b101011100110000 1
b1011100110000 B
1%
#2740000
0%
#2750000
b1001010111 "
b1001010111 C
b1011110110000 9
b101011101110000 6
b101011101110000 1
b1011101110000 B
1%
#2760000
0%
#2770000
b1011111110000 9
b101011110110000 6
b101011110110000 1
b1011110110000 B
1%
#2780000
0%
#2790000
b1100000110000 9
b101011111110000 6
b101011111110000 1
b1011111110000 B
1%
#2800000
0%
#2810000
b1001011000 8
b1100001110000 9
b101100000110000 6
b101100000110000 1
b1100000110000 B
1%
#2820000
0%
#2830000
b1001011000 "
b1001011000 C
b1100010110000 9
b101100001110000 6
b101100001110000 1
b1100001110000 B
1%
#2840000
0%
#2850000
b1100011110000 9
b101100010110000 6
b101100010110000 1
b1100010110000 B
1%
#2860000
0%
#2870000
b1100100110000 9
b101100011110000 6
b101100011110000 1
b1100011110000 B
1%
#2880000
0%
#2890000
b1001011001 8
b1100101110000 9
b101100100110000 6
b101100100110000 1
b1100100110000 B
1%
#2900000
0%
#2910000
b1001011001 "
b1001011001 C
b1100110110000 9
b101100101110000 6
b101100101110000 1
b1100101110000 B
1%
#2920000
0%
#2930000
b1100111110000 9
b101100110110000 6
b101100110110000 1
b1100110110000 B
1%
#2940000
0%
#2950000
b1101000110000 9
b101100111110000 6
b101100111110000 1
b1100111110000 B
1%
#2960000
0%
#2970000
b1001011010 8
b1101001110000 9
b101101000110000 6
b101101000110000 1
b1101000110000 B
1%
#2980000
0%
#2990000
b1001011010 "
b1001011010 C
b1101010110000 9
b101101001110000 6
b101101001110000 1
b1101001110000 B
1%
#3000000
0%
#3010000
b1101011110000 9
b101101010110000 6
b101101010110000 1
b1101010110000 B
1%
#3020000
0%
#3030000
b1101100110000 9
b101101011110000 6
b101101011110000 1
b1101011110000 B
1%
#3040000
0%
#3050000
b1001011011 8
b1101101110000 9
b101101100110000 6
b101101100110000 1
b1101100110000 B
1%
#3060000
0%
#3070000
b1001011011 "
b1001011011 C
b1101110110000 9
b101101101110000 6
b101101101110000 1
b1101101110000 B
1%
#3080000
0%
#3090000
b1101111110000 9
b101101110110000 6
b101101110110000 1
b1101110110000 B
1%
#3100000
0%
#3110000
b1110000110000 9
b101101111110000 6
b101101111110000 1
b1101111110000 B
1%
#3120000
0%
#3130000
b1001011100 8
b1110001110000 9
b101110000110000 6
b101110000110000 1
b1110000110000 B
1%
#3140000
0%
#3150000
b1001011100 "
b1001011100 C
b1110010110000 9
b101110001110000 6
b101110001110000 1
b1110001110000 B
1%
#3160000
0%
#3170000
b1110011110000 9
b101110010110000 6
b101110010110000 1
b1110010110000 B
1%
#3180000
0%
#3190000
b1110100110000 9
b101110011110000 6
b101110011110000 1
b1110011110000 B
1%
#3200000
0%
#3210000
b1001011101 8
b1110101110000 9
b101110100110000 6
b101110100110000 1
b1110100110000 B
1%
#3220000
0%
#3230000
b1001011101 "
b1001011101 C
b1110110110000 9
b101110101110000 6
b101110101110000 1
b1110101110000 B
1%
#3240000
0%
#3250000
b1110111110000 9
b101110110110000 6
b101110110110000 1
b1110110110000 B
1%
#3260000
0%
#3270000
b1111000110000 9
b101110111110000 6
b101110111110000 1
b1110111110000 B
1%
#3280000
0%
#3290000
b1001011110 8
b1111001110000 9
b101111000110000 6
b101111000110000 1
b1111000110000 B
1%
#3300000
0%
#3310000
b1001011110 "
b1001011110 C
b1111010110000 9
b101111001110000 6
b101111001110000 1
b1111001110000 B
1%
#3320000
0%
#3330000
b1111011110000 9
b101111010110000 6
b101111010110000 1
b1111010110000 B
1%
#3340000
0%
#3350000
b1111100110000 9
b101111011110000 6
b101111011110000 1
b1111011110000 B
1%
#3360000
0%
#3370000
b1001011111 8
b1111101110000 9
b101111100110000 6
b101111100110000 1
b1111100110000 B
1%
#3380000
0%
#3390000
b1001011111 "
b1001011111 C
b1111110110000 9
b101111101110000 6
b101111101110000 1
b1111101110000 B
1%
#3400000
0%
#3410000
b1111111110000 9
b101111110110000 6
b101111110110000 1
b1111110110000 B
1%
#3420000
0%
#3430000
b10000000110000 9
b101111111110000 6
b101111111110000 1
b1111111110000 B
1%
#3440000
0%
#3450000
b1001100000 8
b10000001110000 9
b110000000110000 6
b110000000110000 1
b10000000110000 B
1%
#3460000
0%
#3470000
b1001100000 "
b1001100000 C
b10000010110000 9
b110000001110000 6
b110000001110000 1
b10000001110000 B
1%
#3480000
0%
#3490000
b10000011110000 9
b110000010110000 6
b110000010110000 1
b10000010110000 B
1%
#3500000
0%
#3510000
b10000100110000 9
b110000011110000 6
b110000011110000 1
b10000011110000 B
1%
#3520000
0%
#3530000
b1001100001 8
b10000101110000 9
b110000100110000 6
b110000100110000 1
b10000100110000 B
1%
#3540000
0%
#3550000
b1001100001 "
b1001100001 C
b10000110110000 9
b110000101110000 6
b110000101110000 1
b10000101110000 B
1%
#3560000
0%
#3570000
b10000111110000 9
b110000110110000 6
b110000110110000 1
b10000110110000 B
1%
#3580000
0%
#3590000
b10001000110000 9
b110000111110000 6
b110000111110000 1
b10000111110000 B
1%
#3600000
0%
#3610000
b1001100010 8
b10001001110000 9
b110001000110000 6
b110001000110000 1
b10001000110000 B
1%
#3620000
0%
#3630000
b1001100010 "
b1001100010 C
b10001010110000 9
b110001001110000 6
b110001001110000 1
b10001001110000 B
1%
#3640000
0%
#3650000
b10001011110000 9
b110001010110000 6
b110001010110000 1
b10001010110000 B
1%
#3660000
0%
#3670000
b10001100110000 9
b110001011110000 6
b110001011110000 1
b10001011110000 B
1%
#3680000
0%
#3690000
b1001100011 8
b10001101110000 9
b110001100110000 6
b110001100110000 1
b10001100110000 B
1%
#3700000
0%
#3710000
b1001100011 "
b1001100011 C
b10001110110000 9
b110001101110000 6
b110001101110000 1
b10001101110000 B
1%
#3720000
0%
#3730000
b10001111110000 9
b110001110110000 6
b110001110110000 1
b10001110110000 B
1%
#3740000
0%
#3750000
b10010000110000 9
b110001111110000 6
b110001111110000 1
b10001111110000 B
1%
#3760000
0%
#3770000
b1001100100 8
b10010001110000 9
b110010000110000 6
b110010000110000 1
b10010000110000 B
1%
#3780000
0%
