src/lfsr_dither.v
// CHIPATHON 2026
//! @title LFSR Generator for Dithering
//! @author Muhammad Shofuwan Anwar, Ferhad Zulfas, Hardian Tri Pamungkas, Maulidan Imtinan Ahmada

module lfsr_dither #(
    parameter integer OUT_W  = 6,         //! Output width
    parameter integer STEP_N = 7         //! Steps per clock
)(
    input  wire                     clk_ref,        //! Reference clock
    input  wire                     rst_n,          //! Async reset
    input  wire                     en,             //! Enable/freeze
    input  wire [2:0]               cfg_amp_shift,  //! Amplitude control
    output wire signed [OUT_W-1:0]  dither          //! Dither output
);

    localparam [15:0] SEED = 16'hACE1;   //! Initial state

    //! One LFSR step
    function [15:0] lfsr_step(input [15:0] s);
        lfsr_step = {s[14:0], s[15] ^ s[14] ^ s[12] ^ s[3]};
    endfunction

    reg  [15:0] state;  //! Current state
    reg  [15:0] nxt;    //! Next state

    integer i;
    always @(*) begin : compute_next
        nxt = state;
        for (i = 0; i < STEP_N; i = i + 1)
            nxt = lfsr_step(nxt);
    end

    always @(posedge clk_ref or negedge rst_n) begin : update_state
        if (!rst_n)  
            state <= SEED;      
        else if (en) 
            state <= nxt;
    end

    wire signed [OUT_W-1:0] raw; //! LFSR_bits

    assign raw = state[OUT_W-1:0];

    assign dither = raw >>> cfg_amp_shift;

endmodule

tb/lfsr_dither_tb.v
`timescale 1ns/1ps

module tb_lfsr_dither;

    // Main testbench signals
    reg clk = 0;
    reg rst_n = 0;
    reg en = 1;
    reg [2:0] amp = 3'd0;
    wire signed [5:0] dither;

    // Monitor variables for self-checking verification
    integer max_val, min_val;
    reg signed [5:0] frozen_val;

    // Clock generator (40ns period / 25MHz)
    always #20 clk = ~clk;

    // LFSR Dither Device Under Test (DUT) Instantiation
    lfsr_dither #(
        .OUT_W(6), 
        .STEP_N(7)
    ) dut (
        .clk_ref(clk), 
        .rst_n(rst_n), 
        .en(en),
        .cfg_amp_shift(amp), 
        .dither(dither)
    );

    // Monitor block to track maximum and minimum amplitude boundaries
    always @(posedge clk) begin
        if (rst_n && en) begin
            if (dither > max_val) max_val = dither;
            if (dither < min_val) min_val = dither;
        end
    end

    // Task to reset the min/max monitor for the next test scenario
    task reset_monitor;
        begin
            max_val = -999;
            min_val =  999;
        end
    endtask

    initial begin
        // Setup VCD dump for waveform analysis (GTKWave/ModelSim)
        $dumpfile("lfsr_dither_tb.vcd");
        $dumpvars(0, tb_lfsr_dither);
        
        $display("=============================================================");
        $display("STARTING LFSR DITHER VERIFICATION (MBG32)");
        $display("=============================================================");

        // INITIAL CONDITION: Assert reset
        rst_n = 0;
        en = 1;
        amp = 3'd0;
        reset_monitor();
        #100;

        // TEST 1: Full Amplitude (amp = 0)
        $display("[TEST 1] Full Amplitude Mode (amp = 0)");
        rst_n = 1; // Release reset
        #4000;
        $display("-> Observed Range: Min = %0d, Max = %0d", min_val, max_val);

        // TEST 2: Attenuated Mode (amp = 1)
        // Expected behavior: The amplitude range should be halved
        $display("[TEST 2] Attenuated Mode (amp = 1)");
        reset_monitor();
        amp = 3'd1;
        #4000;
        $display("-> Observed Range: Min = %0d, Max = %0d", min_val, max_val);

        // TEST 3: Attenuated Mode (amp = 2)
        // Expected behavior: The amplitude range should be quartered
        $display("[TEST 3] Attenuated Mode (amp = 2)");
        reset_monitor();
        amp = 3'd2;
        #4000;
        $display("-> Observed Range: Min = %0d, Max = %0d", min_val, max_val);

        // TEST 4: Freeze Feature Verification (en = 0)
        $display("[TEST 4] Freeze Feature (en = 0)");
        en = 0;
        frozen_val = dither; // Capture the current state
        #1000;
        if (dither == frozen_val)
            $display("-> PASSED: Output is successfully frozen at %0d", dither);
        else
            $display("-> FAILED: Output changed during freeze!");

        // TEST 5: Unfreeze Feature (en = 1)
        $display("[TEST 5] Unfreeze Feature (en = 1)");
        en = 1;
        #1000;

        $display("=============================================================");
        $display("VERIFICATION COMPLETE");
        $display("=============================================================");
        $finish;
    end

endmodule

tb/lfsr_dither_tb.vcd
$date
	Fri Jul 10 20:23:32 2026
$end
$version
	Icarus Verilog
$end
$timescale
	1ps
$end
$scope module tb_lfsr_dither $end
$var wire 6 ! dither [5:0] $end
$var reg 3 " amp [2:0] $end
$var reg 1 # clk $end
$var reg 1 $ en $end
$var reg 6 % frozen_val [5:0] $end
$var reg 1 & rst_n $end
$var integer 32 ' max_val [31:0] $end
$var integer 32 ( min_val [31:0] $end
$scope module dut $end
$var wire 3 ) cfg_amp_shift [2:0] $end
$var wire 1 # clk_ref $end
$var wire 1 $ en $end
$var wire 1 & rst_n $end
$var wire 6 * raw [5:0] $end
$var wire 6 + dither [5:0] $end
$var parameter 32 , OUT_W $end
$var parameter 16 - SEED $end
$var parameter 32 . STEP_N $end
$var reg 16 / nxt [15:0] $end
$var reg 16 0 state [15:0] $end
$var integer 32 1 i [31:0] $end
$scope function lfsr_step $end
$var reg 16 2 s [15:0] $end
$upscope $end
$scope begin compute_next $end
$upscope $end
$scope begin update_state $end
$upscope $end
$upscope $end
$scope task reset_monitor $end
$upscope $end
$upscope $end
$enddefinitions $end
$comment Show the parameter values. $end
$dumpall
b111 .
b1010110011100001 -
b110 ,
$end
#0
$dumpvars
b11100001100010 2
b111 1
b1010110011100001 0
b111000011000101 /
b100001 +
b100001 *
b0 )
b1111100111 (
b11111111111111111111110000011001 '
0&
bx %
1$
0#
b0 "
b100001 !
$end
#20000
1#
#40000
0#
#60000
1#
#80000
0#
#100000
b110001010100001 /
b11000101010000 2
b111 1
b101 !
b101 +
b101 *
b111000011000101 0
b11111111111111111111111111100001 (
b11111111111111111111111111100001 '
1#
1&
#120000
0#
#140000
b101000011010100 /
b1010100001101010 2
b111 1
b100001 !
b100001 +
b100001 *
b110001010100001 0
b101 '
1#
#160000
0#
#180000
b110101000011010 /
b11010100001101 2
b111 1
b10100 !
b10100 +
b10100 *
b101000011010100 0
1#
#200000
0#
#220000
b110100100101 /
b1000011010010010 2
b111 1
b11010 !
b11010 +
b11010 *
b110101000011010 0
b10100 '
1#
#240000
0#
#260000
b1001001010010110 /
b100100101001011 2
b111 1
b100101 !
b100101 +
b100101 *
b110100100101 0
b11010 '
1#
#280000
0#
#300000
b100101100100011 /
b1010010110010001 2
b111 1
b10110 !
b10110 +
b10110 *
b1001001010010110 0
1#
#320000
0#
#340000
b1001000111011111 /
b1100100011101111 2
b111 1
b100011 !
b100011 +
b100011 *
b100101100100011 0
1#
#360000
0#
#380000
b1110111111100000 /
b111011111110000 2
b111 1
b11111 !
b11111 +
b11111 *
b1001000111011111 0
1#
#400000
0#
#420000
b1111000000100101 /
b1111100000010010 2
b111 1
b100000 !
b100000 +
b100000 *
b1110111111100000 0
b11111 '
1#
#440000
0#
#460000
b1001011100110 /
b100101110011 2
b111 1
b100101 !
b100101 +
b100101 *
b1111000000100101 0
b11111111111111111111111111100000 (
1#
#480000
0#
#500000
b111001101100110 /
b1011100110110011 2
b111 1
b100110 !
b100110 +
b100110 *
b1001011100110 0
1#
#520000
0#
#540000
b1011001100110100 /
b1101100110011010 2
b111 1
b111001101100110 0
1#
#560000
0#
#580000
b1001101000000110 /
b1100110100000011 2
b111 1
b110100 !
b110100 +
b110100 *
b1011001100110100 0
1#
#600000
0#
#620000
b1100001111 /
b1000000110000111 2
b111 1
b110 !
b110 +
b110 *
b1001101000000110 0
1#
#640000
0#
#660000
b1000011111110001 /
b1100001111111000 2
b111 1
b1111 !
b1111 +
b1111 *
b1100001111 0
1#
#680000
0#
#700000
b1111100011010110 /
b1111110001101011 2
b111 1
b110001 !
b110001 +
b110001 *
b1000011111110001 0
1#
#720000
0#
#740000
b110101101010010 /
b11010110101001 2
b111 1
b10110 !
b10110 +
b10110 *
b1111100011010110 0
1#
#760000
0#
#780000
b1010100101100101 /
b1101010010110010 2
b111 1
b10010 !
b10010 +
b10010 *
b110101101010010 0
1#
#800000
0#
#820000
b1011001011110111 /
b101100101111011 2
b111 1
b100101 !
b100101 +
b100101 *
b1010100101100101 0
1#
#840000
0#
#860000
b111101110011001 /
b1011110111001100 2
b111 1
b110111 !
b110111 +
b110111 *
b1011001011110111 0
1#
#880000
0#
#900000
b1100110011100110 /
b1110011001110011 2
b111 1
b11001 !
b11001 +
b11001 *
b111101110011001 0
1#
#920000
0#
#940000
b111001100101011 /
b11100110010101 2
b111 1
b100110 !
b100110 +
b100110 *
b1100110011100110 0
1#
#960000
0#
#980000
b1001010111011011 /
b1100101011101101 2
b111 1
b101011 !
b101011 +
b101011 *
b111001100101011 0
1#
#1000000
0#
#1020000
b1110110111010101 /
b111011011101010 2
b111 1
b11011 !
b11011 +
b11011 *
b1001010111011011 0
1#
#1040000
0#
#1060000
b1110101010000100 /
b111010101000010 2
b111 1
b10101 !
b10101 +
b10101 *
b1110110111010101 0
1#
#1080000
0#
#1100000
b100001000010100 /
b1010000100001010 2
b111 1
b100 !
b100 +
b100 *
b1110101010000100 0
1#
#1120000
0#
#1140000
b101001001111 /
b1000010100100111 2
b111 1
b10100 !
b10100 +
b10100 *
b100001000010100 0
1#
#1160000
0#
#1180000
b10011111011011 /
b1001001111101101 2
b111 1
b1111 !
b1111 +
b1111 *
b101001001111 0
1#
#1200000
0#
#1220000
b1110110111110100 /
b1111011011111010 2
b111 1
b11011 !
b11011 +
b11011 *
b10011111011011 0
1#
#1240000
0#
#1260000
b1111101000001100 /
b111110100000110 2
b111 1
b110100 !
b110100 +
b110100 *
b1110110111110100 0
1#
#1280000
0#
#1300000
b11000001111 /
b1000001100000111 2
b111 1
b1100 !
b1100 +
b1100 *
b1111101000001100 0
1#
#1320000
0#
#1340000
b11111100011 /
b1000001111110001 2
b111 1
b1111 !
b1111 +
b1111 *
b11000001111 0
1#
#1360000
0#
#1380000
b1111000110000011 /
b1111100011000001 2
b111 1
b100011 !
b100011 +
b100011 *
b11111100011 0
1#
#1400000
0#
#1420000
b1100000111010010 /
b110000011101001 2
b111 1
b11 !
b11 +
b11 *
b1111000110000011 0
1#
#1440000
0#
#1460000
b1110100100110101 /
b111010010011010 2
b111 1
b10010 !
b10010 +
b10010 *
b1100000111010010 0
1#
#1480000
0#
#1500000
b1001101010010000 /
b100110101001000 2
b111 1
b110101 !
b110101 +
b110101 *
b1110100100110101 0
1#
#1520000
0#
#1540000
b100100000111110 /
b1010010000011111 2
b111 1
b10000 !
b10000 +
b10000 *
b1001101010010000 0
1#
#1560000
0#
#1580000
b1111100111111 /
b111110011111 2
b111 1
b111110 !
b111110 +
b111110 *
b100100000111110 0
1#
#1600000
0#
#1620000
b1001111110010101 /
b1100111111001010 2
b111 1
b111111 !
b111111 +
b111111 *
b1111100111111 0
1#
#1640000
0#
#1660000
b1100101010000110 /
b1110010101000011 2
b111 1
b10101 !
b10101 +
b10101 *
b1001111110010101 0
1#
#1680000
0#
#1700000
b100001100110110 /
b1010000110011011 2
b111 1
b110 !
b110 +
b110 *
b1100101010000110 0
1#
#1720000
0#
#1740000
b1001101101011011 /
b1100110110101101 2
b111 1
b110110 !
b110110 +
b110110 *
b100001100110110 0
1#
#1760000
0#
#1780000
b1010110111100101 /
b1101011011110010 2
b111 1
b11011 !
b11011 +
b11011 *
b1001101101011011 0
1#
#1800000
0#
#1820000
b1111001011100010 /
b111100101110001 2
b111 1
b100101 !
b100101 +
b100101 *
b1010110111100101 0
1#
#1840000
0#
#1860000
b111000101010101 /
b1011100010101010 2
b111 1
b100010 !
b100010 +
b100010 *
b1111001011100010 0
1#
#1880000
0#
#1900000
b1010101010100110 /
b101010101010011 2
b111 1
b10101 !
b10101 +
b10101 *
b111000101010101 0
1#
#1920000
0#
#1940000
b101001101100011 /
b1010100110110001 2
b111 1
b100110 !
b100110 +
b100110 *
b1010101010100110 0
1#
#1960000
0#
#1980000
b1011000110101101 /
b1101100011010110 2
b111 1
b100011 !
b100011 +
b100011 *
b101001101100011 0
1#
#2000000
0#
#2020000
b1101011011000011 /
b110101101100001 2
b111 1
b101101 !
b101101 +
b101101 *
b1011000110101101 0
1#
#2040000
0#
#2060000
b110000111111001 /
b1011000011111100 2
b111 1
b11 !
b11 +
b11 *
b1101011011000011 0
1#
#2080000
0#
#2100000
b1111110010011111 /
b111111001001111 2
b111 1
b111001 !
b111001 +
b111001 *
b110000111111001 0
1#
#2120000
0#
#2140000
b100111110001000 /
b10011111000100 2
b111 1
b11111 !
b11111 +
b11111 *
b1111110010011111 0
1#
#2160000
0#
#2180000
b1100010000010111 /
b1110001000001011 2
b111 1
b1000 !
b1000 +
b1000 *
b100111110001000 0
1#
#2200000
0#
#2220000
b101110001110 /
b10111000111 2
b111 1
b10111 !
b10111 +
b10111 *
b1100010000010111 0
1#
#2240000
0#
#2260000
b1100011101010101 /
b1110001110101010 2
b111 1
b1110 !
b1110 +
b1110 *
b101110001110 0
1#
#2280000
0#
#2300000
b1010101010010000 /
b1101010101001000 2
b111 1
b10101 !
b10101 +
b10101 *
b1100011101010101 0
1#
#2320000
0#
#2340000
b100100001010000 /
b1010010000101000 2
b111 1
b10000 !
b10000 +
b10000 *
b1010101010010000 0
1#
#2360000
0#
#2380000
b10100001001001 /
b1010000100100 2
b111 1
b100100001010000 0
1#
#2400000
0#
#2420000
b10010011010000 /
b1001001101000 2
b111 1
b1001 !
b1001 +
b1001 *
b10100001001001 0
1#
#2440000
0#
#2460000
b110100000100111 /
b11010000010011 2
b111 1
b10000 !
b10000 +
b10000 *
b10010011010000 0
1#
#2480000
0#
#2500000
b1001111000000 /
b100111100000 2
b111 1
b100111 !
b100111 +
b100111 *
b110100000100111 0
1#
#2520000
0#
#2540000
b1110000001010000 /
b1111000000101000 2
b111 1
b0 !
b0 +
b0 *
b1001111000000 0
1#
#2560000
0#
#2580000
b10100000010000 /
b1010000001000 2
b111 1
b10000 !
b10000 +
b10000 *
b1110000001010000 0
1#
#2600000
0#
#2620000
b100000011101 /
b10000001110 2
b111 1
b10100000010000 0
1#
#2640000
0#
#2660000
b111011000000 /
b11101100000 2
b111 1
b11101 !
b11101 +
b11101 *
b100000011101 0
1#
#2680000
0#
#2700000
b110000000110001 /
b1011000000011000 2
b111 1
b0 !
b0 +
b0 *
b111011000000 0
1#
#2720000
0#
#2740000
b1100011011101 /
b110001101110 2
b111 1
b110001 !
b110001 +
b110001 *
b110000000110001 0
1#
#2760000
0#
#2780000
b110111010011110 /
b11011101001111 2
b111 1
b11101 !
b11101 +
b11101 *
b1100011011101 0
1#
#2800000
0#
#2820000
b100111100010010 /
b1010011110001001 2
b111 1
b11110 !
b11110 +
b11110 *
b110111010011110 0
1#
#2840000
0#
#2860000
b1000100101000000 /
b1100010010100000 2
b111 1
b10010 !
b10010 +
b10010 *
b100111100010010 0
1#
#2880000
0#
#2900000
b1010000001101110 /
b101000000110111 2
b111 1
b0 !
b0 +
b0 *
b1000100101000000 0
1#
#2920000
0#
#2940000
b11011100000001 /
b1101110000000 2
b111 1
b101110 !
b101110 +
b101110 *
b1010000001101110 0
1#
#2960000
0#
#2980000
b1000000011111111 /
b1100000001111111 2
b111 1
b1 !
b1 +
b1 *
b11011100000001 0
1#
#3000000
0#
#3020000
b111111110111000 /
b11111111011100 2
b111 1
b111111 !
b111111 +
b111111 *
b1000000011111111 0
1#
#3040000
0#
#3060000
b1101110001111001 /
b1110111000111100 2
b111 1
b111000 !
b111000 +
b111000 *
b111111110111000 0
1#
#3080000
0#
#3100000
b11110010001011 /
b1111001000101 2
b111 1
b111001 !
b111001 +
b111001 *
b1101110001111001 0
1#
#3120000
0#
#3140000
b100010110001000 /
b10001011000100 2
b111 1
b1011 !
b1011 +
b1011 *
b11110010001011 0
1#
#3160000
0#
#3180000
b1100010000110010 /
b110001000011001 2
b111 1
b1000 !
b1000 +
b1000 *
b100010110001000 0
1#
#3200000
0#
#3220000
b1100100100100 /
b110010010010 2
b111 1
b110010 !
b110010 +
b110010 *
b1100010000110010 0
1#
#3240000
0#
#3260000
b1001001001010100 /
b100100100101010 2
b111 1
b100100 !
b100100 +
b100100 *
b1100100100100 0
1#
#3280000
0#
#3300000
b10101000110001 /
b1001010100011000 2
b111 1
b10100 !
b10100 +
b10100 *
b1001001001010100 0
1#
#3320000
0#
#3340000
b1100010011110 /
b1000110001001111 2
b111 1
b110001 !
b110001 +
b110001 *
b10101000110001 0
1#
#3360000
0#
#3380000
b100111100000110 /
b10011110000011 2
b111 1
b11110 !
b11110 +
b11110 *
b1100010011110 0
1#
#3400000
0#
#3420000
b1000001101100010 /
b1100000110110001 2
b111 1
b110 !
b110 +
b110 *
b100111100000110 0
1#
#3440000
0#
#3460000
b1011000101011010 /
b1101100010101101 2
b111 1
b100010 !
b100010 +
b100010 *
b1000001101100010 0
1#
#3480000
0#
#3500000
b1010110101111011 /
b101011010111101 2
b111 1
b11010 !
b11010 +
b11010 *
b1011000101011010 0
1#
#3520000
0#
#3540000
b1011110110010111 /
b101111011001011 2
b111 1
b111011 !
b111011 +
b111011 *
b1010110101111011 0
1#
#3560000
0#
#3580000
b1100101110101111 /
b110010111010111 2
b111 1
b10111 !
b10111 +
b10111 *
b1011110110010111 0
1#
#3600000
0#
#3620000
b1101011111111111 /
b1110101111111111 2
b111 1
b101111 !
b101111 +
b101111 *
b1100101110101111 0
1#
#3640000
0#
#3660000
b1111111110011010 /
b1111111111001101 2
b111 1
b111111 !
b111111 +
b111111 *
b1101011111111111 0
1#
#3680000
0#
#3700000
b1100110100101100 /
b1110011010010110 2
b111 1
b11010 !
b11010 +
b11010 *
b1111111110011010 0
1#
#3720000
0#
#3740000
b1001011001111000 /
b100101100111100 2
b111 1
b101100 !
b101100 +
b101100 *
b1100110100101100 0
1#
#3760000
0#
#3780000
b11110001000000 /
b1001111000100000 2
b111 1
b111000 !
b111000 +
b111000 *
b1001011001111000 0
1#
#3800000
0#
#3820000
b10000001010110 /
b1000000101011 2
b111 1
b0 !
b0 +
b0 *
b11110001000000 0
1#
#3840000
0#
#3860000
b10101100000001 /
b1010110000000 2
b111 1
b10110 !
b10110 +
b10110 *
b10000001010110 0
1#
#3880000
0#
#3900000
b1000000010011011 /
b1100000001001101 2
b111 1
b1 !
b1 +
b1 *
b10101100000001 0
1#
#3920000
0#
#3940000
b100110110011011 /
b10011011001101 2
b111 1
b11011 !
b11011 +
b11011 *
b1000000010011011 0
1#
#3960000
0#
#3980000
b1100110110000101 /
b110011011000010 2
b111 1
b100110110011011 0
1#
#4000000
0#
#4020000
b1100001010110110 /
b110000101011011 2
b111 1
b101 !
b101 +
b101 *
b1100110110000101 0
1#
#4040000
0#
#4060000
b101101100011000 /
b1010110110001100 2
b111 1
b110110 !
b110110 +
b110110 *
b1100001010110110 0
1#
#4080000
0#
#4100000
b1000110001011111 /
b1100011000101111 2
b111 1
b11000 *
b101101100011000 0
1#
b1100 !
b1100 +
b1 "
b1 )
b11111111111111111111111111111011 (
b11111111111111111111111111111011 '
#4120000
0#
#4140000
b10111110000011 /
b1011111000001 2
b111 1
b1111 !
b1111 +
b11111 *
b1000110001011111 0
b1100 '
1#
#4160000
0#
#4180000
b1100000110011111 /
b1110000011001111 2
b111 1
b1 !
b1 +
b11 *
b10111110000011 0
b1111 '
1#
#4200000
0#
#4220000
b1100111111011010 /
b110011111101101 2
b111 1
b1111 !
b1111 +
b11111 *
b1100000110011111 0
1#
#4240000
0#
#4260000
b1110110101000011 /
b1111011010100001 2
b111 1
b1101 !
b1101 +
b11010 *
b1100111111011010 0
1#
#4280000
0#
#4300000
b1010000110110101 /
b101000011011010 2
b111 1
b1 !
b1 +
b11 *
b1110110101000011 0
1#
#4320000
0#
#4340000
b1101101011011010 /
b110110101101101 2
b111 1
b111010 !
b111010 +
b110101 *
b1010000110110101 0
1#
#4360000
0#
#4380000
b110110100001100 /
b1011011010000110 2
b111 1
b1101 !
b1101 +
b11010 *
b1101101011011010 0
b11111111111111111111111111111010 (
1#
#4400000
0#
#4420000
b1000011000001111 /
b100001100000111 2
b111 1
b110 !
b110 +
b1100 *
b110110100001100 0
1#
#4440000
0#
#4460000
b11110100111 /
b1000001111010011 2
b111 1
b111 !
b111 +
b1111 *
b1000011000001111 0
1#
#4480000
0#
#4500000
b1101001110100000 /
b1110100111010000 2
b111 1
b110011 !
b110011 +
b100111 *
b11110100111 0
1#
#4520000
0#
#4540000
b1101000001110011 /
b1110100000111001 2
b111 1
b110000 !
b110000 +
b100000 *
b1101001110100000 0
b11111111111111111111111111110011 (
1#
#4560000
0#
#4580000
b11100111100111 /
b1110011110011 2
b111 1
b111001 !
b111001 +
b110011 *
b1101000001110011 0
b11111111111111111111111111110000 (
1#
#4600000
0#
#4620000
b1111001111111101 /
b111100111111110 2
b111 1
b110011 !
b110011 +
b100111 *
b11100111100111 0
1#
#4640000
0#
#4660000
b1111111010101111 /
b1111111101010111 2
b111 1
b111110 !
b111110 +
b111101 *
b1111001111111101 0
1#
#4680000
0#
#4700000
b101011110000011 /
b1010101111000001 2
b111 1
b110111 !
b110111 +
b101111 *
b1111111010101111 0
1#
#4720000
0#
#4740000
b1100000110111001 /
b1110000011011100 2
b111 1
b1 !
b1 +
b11 *
b101011110000011 0
1#
#4760000
0#
#4780000
b1101110011101001 /
b110111001110100 2
b111 1
b111100 !
b111100 +
b111001 *
b1100000110111001 0
1#
#4800000
0#
#4820000
b111010010001001 /
b11101001000100 2
b111 1
b110100 !
b110100 +
b101001 *
b1101110011101001 0
1#
#4840000
0#
#4860000
b100010011010001 /
b10001001101000 2
b111 1
b100 !
b100 +
b1001 *
b111010010001001 0
1#
#4880000
0#
#4900000
b110100011111010 /
b11010001111101 2
b111 1
b1000 !
b1000 +
b10001 *
b100010011010001 0
1#
#4920000
0#
#4940000
b111110100101101 /
b11111010010110 2
b111 1
b111101 !
b111101 +
b111010 *
b110100011111010 0
1#
#4960000
0#
#4980000
b1001011011011010 /
b100101101101101 2
b111 1
b110110 !
b110110 +
b101101 *
b111110100101101 0
1#
#5000000
0#
#5020000
b110110101010011 /
b1011011010101001 2
b111 1
b1101 !
b1101 +
b11010 *
b1001011011011010 0
1#
#5040000
0#
#5060000
b1010100111110001 /
b101010011111000 2
b111 1
b1001 !
b1001 +
b10011 *
b110110101010011 0
1#
#5080000
0#
#5100000
b1111100011010111 /
b111110001101011 2
b111 1
b111000 !
b111000 +
b110001 *
b1010100111110001 0
1#
#5120000
0#
#5140000
b110101111011010 /
b11010111101101 2
b111 1
b1011 !
b1011 +
b10111 *
b1111100011010111 0
1#
#5160000
0#
#5180000
b1110110100100011 /
b1111011010010001 2
b111 1
b1101 !
b1101 +
b11010 *
b110101111011010 0
1#
#5200000
0#
#5220000
b1001000110110100 /
b100100011011010 2
b111 1
b110001 !
b110001 +
b100011 *
b1110110100100011 0
1#
#5240000
0#
#5260000
b1101101000111100 /
b110110100011110 2
b111 1
b111010 !
b111010 +
b110100 *
b1001000110110100 0
1#
#5280000
0#
#5300000
b1111000111100 /
b1000111100011110 2
b111 1
b111110 !
b111110 +
b111100 *
b1101101000111100 0
1#
#5320000
0#
#5340000
b1111000001001 /
b1000111100000100 2
b111 1
b1111000111100 0
1#
#5360000
0#
#5380000
b10010100011 /
b1000001001010001 2
b111 1
b100 !
b100 +
b1001 *
b1111000001001 0
1#
#5400000
0#
#5420000
b101000110001100 /
b10100011000110 2
b111 1
b110001 !
b110001 +
b100011 *
b10010100011 0
1#
#5440000
0#
#5460000
b1100011001011010 /
b110001100101101 2
b111 1
b110 !
b110 +
b1100 *
b101000110001100 0
1#
#5480000
0#
#5500000
b10110101101010 /
b1001011010110101 2
b111 1
b1101 !
b1101 +
b11010 *
b1100011001011010 0
1#
#5520000
0#
#5540000
b1011010101011011 /
b101101010101101 2
b111 1
b110101 !
b110101 +
b101010 *
b10110101101010 0
1#
#5560000
0#
#5580000
b1010110111100100 /
b101011011110010 2
b111 1
b1101 !
b1101 +
b11011 *
b1011010101011011 0
1#
#5600000
0#
#5620000
b1111001001101010 /
b111100100110101 2
b111 1
b110010 !
b110010 +
b100100 *
b1010110111100100 0
1#
#5640000
0#
#5660000
b11010100010011 /
b1001101010001001 2
b111 1
b110101 !
b110101 +
b101010 *
b1111001001101010 0
1#
#5680000
0#
#5700000
b1000100111100101 /
b100010011110010 2
b111 1
b1001 !
b1001 +
b10011 *
b11010100010011 0
1#
#5720000
0#
#5740000
b1111001011000110 /
b111100101100011 2
b111 1
b110010 !
b110010 +
b100101 *
b1000100111100101 0
1#
#5760000
0#
#5780000
b110001101110111 /
b1011000110111011 2
b111 1
b11 !
b11 +
b110 *
b1111001011000110 0
1#
#5800000
0#
#5820000
b1011101111100001 /
b1101110111110000 2
b111 1
b111011 !
b111011 +
b110111 *
b110001101110111 0
1#
#5840000
0#
#5860000
b1111000010000001 /
b1111100001000000 2
b111 1
b110000 !
b110000 +
b100001 *
b1011101111100001 0
1#
#5880000
0#
#5900000
b100000011000110 /
b10000001100011 2
b111 1
b0 !
b0 +
b1 *
b1111000010000001 0
1#
#5920000
0#
#5940000
b110001101010110 /
b11000110101011 2
b111 1
b11 !
b11 +
b110 *
b100000011000110 0
1#
#5960000
0#
#5980000
b1010101101101001 /
b1101010110110100 2
b111 1
b1011 !
b1011 +
b10110 *
b110001101010110 0
1#
#6000000
0#
#6020000
b1011010010011010 /
b1101101001001101 2
b111 1
b110100 !
b110100 +
b101001 *
b1010101101101001 0
1#
#6040000
0#
#6060000
b100110101101010 /
b10011010110101 2
b111 1
b1101 !
b1101 +
b11010 *
b1011010010011010 0
1#
#6080000
0#
#6100000
b1011010100001110 /
b101101010000111 2
b111 1
b110101 !
b110101 +
b101010 *
b100110101101010 0
1#
#6120000
0#
#6140000
b1000011101001111 /
b100001110100111 2
b111 1
b111 !
b111 +
b1110 *
b1011010100001110 0
1#
#6160000
0#
#6180000
b1010011110100011 /
b1101001111010001 2
b111 1
b1111 *
b1000011101001111 0
1#
#6200000
0#
#6220000
b1101000111110101 /
b1110100011111010 2
b111 1
b110001 !
b110001 +
b100011 *
b1010011110100011 0
1#
#6240000
0#
#6260000
b1111101011010011 /
b111110101101001 2
b111 1
b111010 !
b111010 +
b110101 *
b1101000111110101 0
1#
#6280000
0#
#6300000
b110100111110011 /
b1011010011111001 2
b111 1
b1001 !
b1001 +
b10011 *
b1111101011010011 0
1#
#6320000
0#
#6340000
b1111100111100100 /
b111110011110010 2
b111 1
b111001 !
b111001 +
b110011 *
b110100111110011 0
1#
#6360000
0#
#6380000
b1111001001000110 /
b111100100100011 2
b111 1
b110010 !
b110010 +
b100100 *
b1111100111100100 0
1#
#6400000
0#
#6420000
b10001101110101 /
b1001000110111010 2
b111 1
b11 !
b11 +
b110 *
b1111001001000110 0
1#
#6440000
0#
#6460000
b1011101010010110 /
b1101110101001011 2
b111 1
b111010 !
b111010 +
b110101 *
b10001101110101 0
1#
#6480000
0#
#6500000
b100101100111110 /
b1010010110011111 2
b111 1
b1011 !
b1011 +
b10110 *
b1011101010010110 0
1#
#6520000
0#
#6540000
b1001111100110001 /
b1100111110011000 2
b111 1
b111111 !
b111111 +
b111110 *
b100101100111110 0
1#
#6560000
0#
#6580000
b1001100010100110 /
b1100110001010011 2
b111 1
b111000 !
b111000 +
b110001 *
b1001111100110001 0
1#
#6600000
0#
#6620000
b101001100000110 /
b10100110000011 2
b111 1
b110011 !
b110011 +
b100110 *
b1001100010100110 0
1#
#6640000
0#
#6660000
b1000001100000110 /
b1100000110000011 2
b111 1
b11 !
b11 +
b110 *
b101001100000110 0
1#
#6680000
0#
#6700000
b1000001101111001 /
b1100000110111100 2
b111 1
b1000001100000110 0
1#
#6720000
0#
#6740000
b1011110010000111 /
b1101111001000011 2
b111 1
b111100 !
b111100 +
b111001 *
b1000001101111001 0
1#
#6760000
0#
#6780000
b100001110101010 /
b10000111010101 2
b111 1
b11 !
b11 +
b111 *
b1011110010000111 0
1#
#6800000
0#
#6820000
b1101010100111111 /
b1110101010011111 2
b111 1
b110101 !
b110101 +
b101010 *
b100001110101010 0
1#
#6840000
0#
#6860000
b1001111110010010 /
b100111111001001 2
b111 1
b111111 !
b111111 +
b111111 *
b1101010100111111 0
1#
#6880000
0#
#6900000
b1100100100111101 /
b1110010010011110 2
b111 1
b1001 !
b1001 +
b10010 *
b1001111110010010 0
1#
#6920000
0#
#6940000
b1001111011100111 /
b100111101110011 2
b111 1
b111110 !
b111110 +
b111101 *
b1100100100111101 0
1#
#6960000
0#
#6980000
b111001110010011 /
b1011100111001001 2
b111 1
b110011 !
b110011 +
b100111 *
b1001111011100111 0
1#
#7000000
0#
#7020000
b1100100110011101 /
b1110010011001110 2
b111 1
b1001 !
b1001 +
b10011 *
b111001110010011 0
1#
#7040000
0#
#7060000
b1100111011100101 /
b110011101110010 2
b111 1
b1110 !
b1110 +
b11101 *
b1100100110011101 0
1#
#7080000
0#
#7100000
b111001010111001 /
b1011100101011100 2
b111 1
b110010 !
b110010 +
b100101 *
b1100111011100101 0
1#
#7120000
0#
#7140000
b101110011001101 /
b1010111001100110 2
b111 1
b111100 !
b111100 +
b111001 *
b111001010111001 0
1#
#7160000
0#
#7180000
b110011011101111 /
b11001101110111 2
b111 1
b110 !
b110 +
b1101 *
b101110011001101 0
1#
#7200000
0#
#7220000
b111011110110101 /
b1011101111011010 2
b111 1
b110111 !
b110111 +
b101111 *
b110011011101111 0
1#
#7240000
0#
#7260000
b1101101010111001 /
b1110110101011100 2
b111 1
b111010 !
b111010 +
b110101 *
b111011110110101 0
1#
#7280000
0#
#7300000
b101110010010100 /
b1010111001001010 2
b111 1
b111100 !
b111100 +
b111001 *
b1101101010111001 0
1#
#7320000
0#
#7340000
b100101000100010 /
b10010100010001 2
b111 1
b1010 !
b1010 +
b10100 *
b101110010010100 0
1#
#7360000
0#
#7380000
b1000101010010 /
b1000100010101001 2
b111 1
b110001 !
b110001 +
b100010 *
b100101000100010 0
1#
#7400000
0#
